roveac/__init__.py
roveac/counter_checker.py
roveac/decrementor.py
roveac/extend.py
roveac/isomorphism_hasher.py
roveac/key_generator.py
roveac/mapping_constructor.py
roveac-1.0.2.dist-info/LICENSE
roveac-1.0.2.dist-info/WHEEL
roveac-1.0.2.dist-info/METADATA
roveac-1.0.2.dist-info/RECORD
