Metadata-Version: 2.3
Name: roveac
Version: 1.0.2
Summary: ROVEaC package
Author-email: Adam Lehavi <adamlehavi@gmail.com>
Requires-Dist: networkx >=3.4.2
Requires-Dist: tqdm >=4.67.0
Requires-Dist: sphinx>=7.1.2 ; extra == "doc"
Requires-Dist: sphinx-rtd-theme>=1.3.0rc1 ; extra == "doc"
Project-URL: Documentation, https://ramsey-ove-and-check.readthedocs.io/en/latest/
Project-URL: Homepage, https://github.com/aLehav/ramsey-ove-and-check
Provides-Extra: doc
